MANIFEST.in
README.rst
buildout.cfg
setup.py
travis.cfg
versions.cfg
bobtemplates/__init__.py
bobtemplates.fon.egg-info/PKG-INFO
bobtemplates.fon.egg-info/SOURCES.txt
bobtemplates.fon.egg-info/dependency_links.txt
bobtemplates.fon.egg-info/namespace_packages.txt
bobtemplates.fon.egg-info/not-zip-safe
bobtemplates.fon.egg-info/requires.txt
bobtemplates.fon.egg-info/top_level.txt
bobtemplates/plone/.gitignore
bobtemplates/plone/.mrbob.ini
bobtemplates/plone/.travis.yml.bob
bobtemplates/plone/MANIFEST.in.bob
bobtemplates/plone/Makefile
bobtemplates/plone/README.rst.bob
bobtemplates/plone/bootstrap.py
bobtemplates/plone/buildout.cfg.bob
bobtemplates/plone/setup.py.bob
bobtemplates/plone/travis.cfg
bobtemplates/plone/buildout.d/base.cfg.bob
bobtemplates/plone/buildout.d/dev.cfg.bob
bobtemplates/plone/buildout.d/sources.cfg
bobtemplates/plone/buildout.d/versions.cfg
bobtemplates/plone/docs/CHANGES.rst.bob
bobtemplates/plone/docs/CONTRIBUTORS.rst.bob
bobtemplates/plone/docs/LICENSE.rst.bob
bobtemplates/plone/docs/api.rst.bob
bobtemplates/plone/docs/conf.py.bob
bobtemplates/plone/docs/glossary.rst.bob
bobtemplates/plone/docs/index.rst.bob
bobtemplates/plone/docs/_static/.gitkeep
bobtemplates/plone/src/+package.namespace+/__init__.py
bobtemplates/plone/src/+package.namespace+/+package.name+/__init__.py.bob
bobtemplates/plone/src/+package.namespace+/+package.name+/configure.zcml.bob
bobtemplates/plone/src/+package.namespace+/+package.name+/interfaces.py.bob
bobtemplates/plone/src/+package.namespace+/+package.name+/setuphandlers.py.bob
bobtemplates/plone/src/+package.namespace+/+package.name+/testing.py.bob
bobtemplates/plone/src/+package.namespace+/+package.name+/testing.zcml.bob
bobtemplates/plone/src/+package.namespace+/+package.name+/browser/__init__.py
bobtemplates/plone/src/+package.namespace+/+package.name+/browser/configure.zcml.bob
bobtemplates/plone/src/+package.namespace+/+package.name+/browser/overrides/.gitkeep
bobtemplates/plone/src/+package.namespace+/+package.name+/browser/static/.gitkeep
bobtemplates/plone/src/+package.namespace+/+package.name+/content/__init__.py
bobtemplates/plone/src/+package.namespace+/+package.name+/content/configure.zcml.bob
