Metadata-Version: 1.1
Name: bobtemplates.fon
Version: 0.3
Summary: Templates for fon projects
Home-page: https://github.com/fngaha/bobtemplates.fon
Author: Franck NGAHA
Author-email: franck.o.ngaha@gmail.com
License: GPL V2
Keywords: Web Python Zope Plone Templates mr.bob
Platform: UNKNOWN
Classifier: Programming Language :: Python
Classifier: Topic :: Software Development :: Libraries :: Python Modules
